dash_insights/__init__.py
dash_insights-0.0.1.dist-info/LICENSE
dash_insights-0.0.1.dist-info/METADATA
dash_insights-0.0.1.dist-info/WHEEL
dash_insights-0.0.1.dist-info/top_level.txt
dash_insights-0.0.1.dist-info/RECORD
