Metadata-Version: 2.1
Name: dash-insights
Version: 0.0.1
Summary: A public stub for dash-insights by Plotly
Home-page: https://plotly.com/dash/
Author: Alex Johnson
Author-email: alex@plotly.com
License: Commercial
Platform: UNKNOWN
Classifier: Programming Language :: Python :: 3
Classifier: Framework :: Dash
